acp_amp/__init__.py
acp_amp/cli.py
acp_amp/server.py
acp_amp/shim.py
acp_amp/driver/base.py
acp_amp/driver/node_sdk.py
acp_amp/driver/python_sdk.py
acp_amp/mapping/to_acp.py
acp_amp/mapping/to_amp.py
acp_amp-0.1.3.dist-info/licenses/LICENSE
acp_amp-0.1.3.dist-info/licenses/NOTICE
acp_amp-0.1.3.dist-info/METADATA
acp_amp-0.1.3.dist-info/WHEEL
acp_amp-0.1.3.dist-info/entry_points.txt
acp_amp-0.1.3.dist-info/top_level.txt
acp_amp-0.1.3.dist-info/RECORD
