Metadata-Version: 2.4
Name: acp-amp
Version: 0.1.3
Summary: ACP adapter that bridges Amp Code to Agent Client Protocol
Author-email: Shashi Jagtap <info@super-agentic.ai>
Maintainer-email: Shashi Jagtap <info@super-agentic.ai>
License: MIT
Project-URL: Homepage, https://github.com/SuperagenticAI/acp-amp
Project-URL: Repository, https://github.com/SuperagenticAI/acp-amp
Project-URL: Issues, https://github.com/SuperagenticAI/acp-amp/issues
Project-URL: Documentation, https://github.com/SuperagenticAI/acp-amp
Keywords: acp,agent-client-protocol,amp,adapter,zed,superqode
Classifier: Development Status :: 3 - Alpha
Classifier: Intended Audience :: Developers
Classifier: License :: OSI Approved :: MIT License
Classifier: Programming Language :: Python :: 3
Classifier: Programming Language :: Python :: 3 :: Only
Classifier: Programming Language :: Python :: 3.10
Classifier: Programming Language :: Python :: 3.11
Classifier: Programming Language :: Python :: 3.12
Classifier: Topic :: Software Development :: Libraries
Requires-Python: >=3.10
License-File: LICENSE
License-File: NOTICE
Requires-Dist: agent-client-protocol>=0.7.1
Requires-Dist: amp-sdk>=0.0.2
Provides-Extra: test
Requires-Dist: pytest>=7.0; extra == "test"
Provides-Extra: docs
Requires-Dist: mkdocs>=1.5; extra == "docs"
Requires-Dist: mkdocs-material>=9.5; extra == "docs"
Dynamic: license-file
